agent_memory_client/__init__.py
agent_memory_client/client.py
agent_memory_client/exceptions.py
agent_memory_client/filters.py
agent_memory_client/models.py
agent_memory_client/py.typed
agent_memory_client/integrations/__init__.py
agent_memory_client/integrations/langchain.py
agent_memory_client-0.13.0.dist-info/METADATA
agent_memory_client-0.13.0.dist-info/WHEEL
agent_memory_client-0.13.0.dist-info/licenses/LICENSE
agent_memory_client-0.13.0.dist-info/RECORD
